amnes/LICENSE
amnes/THIRDPARTY
amnes/__init__.py
amnes/__main__.py
amnes/cli/__init__.py
amnes/cli/config.py
amnes/cli/controller.py
amnes/cli/ctl.py
amnes/cli/utils.py
amnes/cli/worker.py
amnes/core/__init__.py
amnes/core/amnes_object.py
amnes/core/amnes_project.py
amnes/core/experiment.py
amnes/core/experiment_node.py
amnes/core/experiment_sequence.py
amnes/core/experiment_stage.py
amnes/core/node_task.py
amnes/core/parameter_set.py
amnes/core/worker_endpoint.py
amnes/data/__init__.py
amnes/data/database/__init__.py
amnes/data/database/database_abstract.py
amnes/data/database/database_adapter.py
amnes/data/manager/__init__.py
amnes/data/manager/storage_backend.py
amnes/data/manager/storage_backend_peewee.py
amnes/data/models/__init__.py
amnes/data/models/amnes_object.py
amnes/data/models/amnes_project.py
amnes/data/models/base.py
amnes/data/models/experiment_node.py
amnes/data/models/experiment_sequence.py
amnes/data/models/file.py
amnes/data/models/node_task.py
amnes/data/models/parameter_set.py
amnes/data/models/worker_endpoint.py
amnes/data/models/experiment/__init__.py
amnes/data/models/experiment/base.py
amnes/data/models/experiment/experiment_concrete.py
amnes/data/models/experiment/experiment_template.py
amnes/data/serializer/__init__.py
amnes/data/serializer/amnes_object.py
amnes/data/serializer/amnes_project.py
amnes/data/serializer/base.py
amnes/data/serializer/experiment.py
amnes/data/serializer/experiment_node.py
amnes/data/serializer/experiment_sequence.py
amnes/data/serializer/file.py
amnes/data/serializer/node_task.py
amnes/data/serializer/parameter_set.py
amnes/data/serializer/utils.py
amnes/data/serializer/worker_endpoint.py
amnes/exec/__init__.py
amnes/exec/app.py
amnes/exec/config.py
amnes/exec/logging.py
amnes/exec/patcher.py
amnes/exec/controller/__init__.py
amnes/exec/controller/app.py
amnes/exec/controller/config.py
amnes/exec/controller/experiment_execution.py
amnes/exec/controller/project_execution.py
amnes-20.5.1.dist-info/LICENSE
amnes-20.5.1.dist-info/METADATA
amnes-20.5.1.dist-info/WHEEL
amnes-20.5.1.dist-info/entry_points.txt
amnes-20.5.1.dist-info/top_level.txt
amnes-20.5.1.dist-info/RECORD
